seanblend/__init__.py
seanblend/daily_uses.py
seanblend/science/__init__.py
seanblend/science/elements.py
seanblend-0.1.1.dist-info/LICENSE
seanblend-0.1.1.dist-info/METADATA
seanblend-0.1.1.dist-info/WHEEL
seanblend-0.1.1.dist-info/top_level.txt
seanblend-0.1.1.dist-info/RECORD
