Metadata-Version: 2.1
Name: seanblend
Version: 0.1.1
Summary: A Python module by SeanBlend.
Home-page: https://github.com/SeanBlend/SeanBlendModule
Author: SeanBlend
Author-email: seanblend@gmail.com
License: UNKNOWN
Platform: UNKNOWN
Classifier: Programming Language :: Python :: 3
Classifier: License :: OSI Approved :: GNU General Public License v2 or later (GPLv2+)
Classifier: Operating System :: OS Independent
